algobra/__init__.py
algobra/engine.py
algobra/snp500.py
algobra-0.0.3.dist-info/LICENSE.txt
algobra-0.0.3.dist-info/METADATA
algobra-0.0.3.dist-info/WHEEL
algobra-0.0.3.dist-info/top_level.txt
algobra-0.0.3.dist-info/RECORD
