Metadata-Version: 2.1
Name: algobra
Version: 0.0.3
Summary: Python Algorithimic Trading Engine
Home-page: https://twitter.com/bradleycm4
Author: Chris Bradley
Author-email: declarationcb@gmail.com
License: UNKNOWN
Platform: UNKNOWN
Classifier: Programming Language :: Python :: 3.6
Classifier: Programming Language :: Python :: 3.7
Classifier: Operating System :: OS Independent
Classifier: License :: OSI Approved :: GNU General Public License v3 or later (GPLv3+)
Requires-Python: >=3.7
Requires-Dist: numpy
Requires-Dist: requests
Provides-Extra: gpu
Requires-Dist: pyopencl ; extra == 'gpu'
Requires-Dist: six ; extra == 'gpu'
Provides-Extra: testing
Requires-Dist: pytest ; extra == 'testing'
Requires-Dist: torch ; extra == 'testing'
Requires-Dist: tqdm ; extra == 'testing'
